setup.py
pin_functions/__init__.py
pin_functions.egg-info/PKG-INFO
pin_functions.egg-info/SOURCES.txt
pin_functions.egg-info/dependency_links.txt
pin_functions.egg-info/not-zip-safe
pin_functions.egg-info/top_level.txt