Metadata-Version: 1.0
Name: pin-functions
Version: 0.1
Summary: PIN Functions for Infosys Data
Home-page: http://github.com/storborg/funniest
Author: PIN Functions
Author-email: info@3plus.ch
License: MIT
Platform: UNKNOWN
